<?xml version="1.0" encoding="UTF-8"?>
<!DOCTYPE suite SYSTEM "http://testng.org/testng-1.0.dtd">
<suite thread-count="1" guice-stage="DEVELOPMENT" verbose="0" name="Demandware" parallel="tests">
  <parameter name="remote.driver.url" value="http://sereti_qe:b9b8a9e1-e525-46af-9c7f-4a11c372b5c5@ondemand.saucelabs.com:80/wd/hub"/>
  <parameter name="tdm.data" value="off"/>
  <parameter name="glue" value="com.dw.automation.steps"/>
  <parameter name="sauce" value="true"/>
  
  <test name="CSR can view teacher&#039;s full name in customer information module">
    <parameter name="features" value="features/InSprint_11.5/DW_CA_CS_CIM.feature"/>
    <parameter name="scenario" value="CSR can view teacher&#039;s full name in customer information module"/>
    <parameter name="driver.capabilities" value="{&#039;version&#039;: &#039;48.0&#039;,&#039;platform&#039;:&#039;Windows 10&#039;,&#039;name&#039;:&#039;DWCA&#039;}"/>
    <parameter name="driver.name" value="Chrome"/>
    <classes>
      <class name="com.scholastic.torque.runner.Run"/>
    </classes>
  </test> <!-- CSR can view teacher's full name in customer information module -->
  <test name="Teacher Name in customer information module with no prefix">
    <parameter name="features" value="features/InSprint_11.5/DW_CA_CS_CIM.feature"/>
    <parameter name="scenario" value="Teacher Name in customer information module with no prefix"/>
    <parameter name="driver.capabilities" value="{&#039;version&#039;: &#039;48.0&#039;,&#039;platform&#039;:&#039;Windows 10&#039;,&#039;name&#039;:&#039;DWCA&#039;}"/>
    <parameter name="driver.name" value="Chrome"/>
    <classes>
      <class name="com.scholastic.torque.runner.Run"/>
    </classes>
  </test> <!-- Teacher Name in customer information module with no prefix -->
  <test name="No apple status information displayed in CustomerInformation module">
    <parameter name="features" value="features/InSprint_11.5/DW_CA_CS_CIM.feature"/>
    <parameter name="scenario" value="No apple status information displayed in CustomerInformation module"/>
    <parameter name="driver.capabilities" value="{&#039;version&#039;: &#039;48.0&#039;,&#039;platform&#039;:&#039;Windows 10&#039;,&#039;name&#039;:&#039;DWCA&#039;}"/>
    <parameter name="driver.name" value="Chrome"/>
    <classes>
      <class name="com.scholastic.torque.runner.Run"/>
    </classes>
  </test> <!-- No apple status information displayed in CustomerInformation module -->
  <test name="CSR can view the Teacher&#039;s School information">
    <parameter name="features" value="features/InSprint_11.5/DW_CA_CS_CIM.feature"/>
    <parameter name="scenario" value="CSR can view the Teacher&#039;s School information"/>
    <parameter name="driver.capabilities" value="{&#039;version&#039;: &#039;48.0&#039;,&#039;platform&#039;:&#039;Windows 10&#039;,&#039;name&#039;:&#039;DWCA&#039;}"/>
    <parameter name="driver.name" value="Chrome"/>
    <classes>
      <class name="com.scholastic.torque.runner.Run"/>
    </classes>
  </test> <!-- CSR can view the Teacher's School information -->
  <test name="CSR can view teacher&#039;s account number">
    <parameter name="features" value="features/InSprint_11.5/DW_CA_CS_CIM.feature"/>
    <parameter name="scenario" value="CSR can view teacher&#039;s account number"/>
    <parameter name="driver.capabilities" value="{&#039;version&#039;: &#039;48.0&#039;,&#039;platform&#039;:&#039;Windows 10&#039;,&#039;name&#039;:&#039;DWCA&#039;}"/>
    <parameter name="driver.name" value="Chrome"/>
    <classes>
      <class name="com.scholastic.torque.runner.Run"/>
    </classes>
  </test> <!-- CSR can view teacher's account number -->
  <test name="CSR can view the Active status for a teacher">
    <parameter name="features" value="features/InSprint_11.5/DW_CA_CS_CIM.feature"/>
    <parameter name="scenario" value="CSR can view the Active status for a teacher"/>
    <parameter name="driver.capabilities" value="{&#039;version&#039;: &#039;48.0&#039;,&#039;platform&#039;:&#039;Windows 10&#039;,&#039;name&#039;:&#039;DWCA&#039;}"/>
    <parameter name="driver.name" value="Chrome"/>
    <classes>
      <class name="com.scholastic.torque.runner.Run"/>
    </classes>
  </test> <!-- CSR can view the Active status for a teacher -->
  <test name="CSR can view the inactive status of a teacher in 3rd container">
    <parameter name="features" value="features/InSprint_11.5/DW_CA_CS_CIM.feature"/>
    <parameter name="scenario" value="CSR can view the inactive status of a teacher in 3rd container"/>
    <parameter name="driver.capabilities" value="{&#039;version&#039;: &#039;48.0&#039;,&#039;platform&#039;:&#039;Windows 10&#039;,&#039;name&#039;:&#039;DWCA&#039;}"/>
    <parameter name="driver.name" value="Chrome"/>
    <classes>
      <class name="com.scholastic.torque.runner.Run"/>
    </classes>
  </test> <!-- CSR can view the inactive status of a teacher in 3rd container -->
  <test name="CSR can view the Temparory Hold Account status of a given teacher beneath the account number">
    <parameter name="features" value="features/InSprint_11.5/DW_CA_CS_CIM.feature"/>
    <parameter name="scenario" value="CSR can view the Temparory Hold Account status of a given teacher beneath the account number"/>
    <parameter name="driver.capabilities" value="{&#039;version&#039;: &#039;48.0&#039;,&#039;platform&#039;:&#039;Windows 10&#039;,&#039;name&#039;:&#039;DWCA&#039;}"/>
    <parameter name="driver.name" value="Chrome"/>
    <classes>
      <class name="com.scholastic.torque.runner.Run"/>
    </classes>
  </test> <!-- CSR can view the Temparory Hold Account status of a given teacher beneath the account number -->
  <test name="CSR can view the [Pre-Paid] account hold status of a given teacher">
    <parameter name="features" value="features/InSprint_11.5/DW_CA_CS_CIM.feature"/>
    <parameter name="scenario" value="CSR can view the [Pre-Paid] account hold status of a given teacher"/>
    <parameter name="driver.capabilities" value="{&#039;version&#039;: &#039;48.0&#039;,&#039;platform&#039;:&#039;Windows 10&#039;,&#039;name&#039;:&#039;DWCA&#039;}"/>
    <parameter name="driver.name" value="Chrome"/>
    <classes>
      <class name="com.scholastic.torque.runner.Run"/>
    </classes>
  </test> <!-- CSR can view the [Pre-Paid] account hold status of a given teacher -->
  <test name="CSR can view the [Held by A/R] account hold status of a given teacher">
    <parameter name="features" value="features/InSprint_11.5/DW_CA_CS_CIM.feature"/>
    <parameter name="scenario" value="CSR can view the [Held by A/R] account hold status of a given teacher"/>
    <parameter name="driver.capabilities" value="{&#039;version&#039;: &#039;48.0&#039;,&#039;platform&#039;:&#039;Windows 10&#039;,&#039;name&#039;:&#039;DWCA&#039;}"/>
    <parameter name="driver.name" value="Chrome"/>
    <classes>
      <class name="com.scholastic.torque.runner.Run"/>
    </classes>
  </test> <!-- CSR can view the [Held by A/R] account hold status of a given teacher -->
  <test name="CSR can view Bonus Bank information in 4th container in Customer Information module">
    <parameter name="features" value="features/InSprint_11.5/DW_CA_CS_CIM.feature"/>
    <parameter name="scenario" value="CSR can view Bonus Bank information in 4th container in Customer Information module"/>
    <parameter name="driver.capabilities" value="{&#039;version&#039;: &#039;48.0&#039;,&#039;platform&#039;:&#039;Windows 10&#039;,&#039;name&#039;:&#039;DWCA&#039;}"/>
    <parameter name="driver.name" value="Chrome"/>
    <classes>
      <class name="com.scholastic.torque.runner.Run"/>
    </classes>
  </test> <!-- CSR can view Bonus Bank information in 4th container in Customer Information module -->
  <test name="CSR can click on Bonus Bank to view the Bonus bank range list">
    <parameter name="features" value="features/InSprint_11.5/DW_CA_CS_CIM.feature"/>
    <parameter name="scenario" value="CSR can click on Bonus Bank to view the Bonus bank range list"/>
    <parameter name="driver.capabilities" value="{&#039;version&#039;: &#039;48.0&#039;,&#039;platform&#039;:&#039;Windows 10&#039;,&#039;name&#039;:&#039;DWCA&#039;}"/>
    <parameter name="driver.name" value="Chrome"/>
    <classes>
      <class name="com.scholastic.torque.runner.Run"/>
    </classes>
  </test> <!-- CSR can click on Bonus Bank to view the Bonus bank range list -->
  <test name="CSR searches for a teacher account with no dollar in Bonus Bank">
    <parameter name="features" value="features/InSprint_11.5/DW_CA_CS_CIM.feature"/>
    <parameter name="scenario" value="CSR searches for a teacher account with no dollar in Bonus Bank"/>
    <parameter name="driver.capabilities" value="{&#039;version&#039;: &#039;48.0&#039;,&#039;platform&#039;:&#039;Windows 10&#039;,&#039;name&#039;:&#039;DWCA&#039;}"/>
    <parameter name="driver.name" value="Chrome"/>
    <classes>
      <class name="com.scholastic.torque.runner.Run"/>
    </classes>
  </test> <!-- CSR searches for a teacher account with no dollar in Bonus Bank -->
  <test name="CSR search for an account number whose has previous bonus bank balance">
    <parameter name="features" value="features/InSprint_11.5/DW_CA_CS_CIM.feature"/>
    <parameter name="scenario" value="CSR search for an account number whose has previous bonus bank balance"/>
    <parameter name="driver.capabilities" value="{&#039;version&#039;: &#039;48.0&#039;,&#039;platform&#039;:&#039;Windows 10&#039;,&#039;name&#039;:&#039;DWCA&#039;}"/>
    <parameter name="driver.name" value="Chrome"/>
    <classes>
      <class name="com.scholastic.torque.runner.Run"/>
    </classes>
  </test> <!-- CSR search for an account number whose has previous bonus bank balance -->
  
  <test name="CSR sees proper error message when on Teacher Module, the  flyer code entered has non alphanumeric characters">
    <parameter name="features" value="features/InSprint_11.5/ParallelRun_DW_CA_CS_OrderEntry_PageValidation.feature"/>
    <parameter name="scenario" value="CSR sees proper error message when on Teacher Module, the  flyer code entered has non alphanumeric characters"/>
    <parameter name="driver.capabilities" value="{&#039;version&#039;: &#039;48.0&#039;,&#039;platform&#039;:&#039;Windows 10&#039;,&#039;name&#039;:&#039;DWCA&#039;}"/>
    <parameter name="driver.name" value="Chrome"/>
    <classes>
      <class name="com.scholastic.torque.runner.Run"/>
    </classes>
  </test> <!-- CSR sees proper error message when on Teacher Module, the  flyer code entered has non alphanumeric characters -->
  <test name="CSR sees proper error message on clicking [Proceed to Checkout] when on Teacher order, Item# and Flyer code  is blank and QTY is entered">
    <parameter name="features" value="features/InSprint_11.5/ParallelRun_DW_CA_CS_OrderEntry_PageValidation.feature"/>
    <parameter name="scenario" value="CSR sees proper error message on clicking [Proceed to Checkout] when on Teacher order, Item# and Flyer code  is blank and QTY is entered"/>
    <parameter name="driver.capabilities" value="{&#039;version&#039;: &#039;48.0&#039;,&#039;platform&#039;:&#039;Windows 10&#039;,&#039;name&#039;:&#039;DWCA&#039;}"/>
    <parameter name="driver.name" value="Chrome"/>
    <classes>
      <class name="com.scholastic.torque.runner.Run"/>
    </classes>
  </test> <!-- CSR sees proper error message on clicking [Proceed to Checkout] when on Teacher order, Item# and Flyer code  is blank and QTY is entered -->
  <test name="CSR sees proper error message on clicking [Proceed to Checkout] when on Teacher order,Valid flyer code is entered ,more than one Item# cell is blank and Qty is entered">
    <parameter name="features" value="features/InSprint_11.5/ParallelRun_DW_CA_CS_OrderEntry_PageValidation.feature"/>
    <parameter name="scenario" value="CSR sees proper error message on clicking [Proceed to Checkout] when on Teacher order,Valid flyer code is entered ,more than one Item# cell is blank and Qty is entered"/>
    <parameter name="driver.capabilities" value="{&#039;version&#039;: &#039;48.0&#039;,&#039;platform&#039;:&#039;Windows 10&#039;,&#039;name&#039;:&#039;DWCA&#039;}"/>
    <parameter name="driver.name" value="Chrome"/>
    <classes>
      <class name="com.scholastic.torque.runner.Run"/>
    </classes>
  </test> <!-- CSR sees proper error message on clicking [Proceed to Checkout] when on Teacher order,Valid flyer code is entered ,more than one Item# cell is blank and Qty is entered -->
  <test name="CSR sees proper error message pop-up on clicking [Proceed to Checkout] when on Teacher order, Item# entered  has one or more speical characters &amp;QTY is entered">
    <parameter name="features" value="features/InSprint_11.5/ParallelRun_DW_CA_CS_OrderEntry_PageValidation.feature"/>
    <parameter name="scenario" value="CSR sees proper error message pop-up on clicking [Proceed to Checkout] when on Teacher order, Item# entered  has one or more speical characters &amp;QTY is entered"/>
    <parameter name="driver.capabilities" value="{&#039;version&#039;: &#039;48.0&#039;,&#039;platform&#039;:&#039;Windows 10&#039;,&#039;name&#039;:&#039;DWCA&#039;}"/>
    <parameter name="driver.name" value="Chrome"/>
    <classes>
      <class name="com.scholastic.torque.runner.Run"/>
    </classes>
  </test> <!-- CSR sees proper error message pop-up on clicking [Proceed to Checkout] when on Teacher order, Item# entered  has one or more speical characters &QTY is entered -->
  <test name="CSR sees proper error message pop-up on clicking [Proceed to Checkout] when on Teacher order, Flyer code is left blank,Item# entered is single integer &amp;QTY is entered">
    <parameter name="features" value="features/InSprint_11.5/ParallelRun_DW_CA_CS_OrderEntry_PageValidation.feature"/>
    <parameter name="scenario" value="CSR sees proper error message pop-up on clicking [Proceed to Checkout] when on Teacher order, Flyer code is left blank,Item# entered is single integer &amp;QTY is entered"/>
    <parameter name="driver.capabilities" value="{&#039;version&#039;: &#039;48.0&#039;,&#039;platform&#039;:&#039;Windows 10&#039;,&#039;name&#039;:&#039;DWCA&#039;}"/>
    <parameter name="driver.name" value="Chrome"/>
    <classes>
      <class name="com.scholastic.torque.runner.Run"/>
    </classes>
  </test> <!-- CSR sees proper error message pop-up on clicking [Proceed to Checkout] when on Teacher order, Flyer code is left blank,Item# entered is single integer &QTY is entered -->
  <test name="CSR sees proper error message on entering the Invalid Flyer code in the flyer text box for Teacher Order Module on tabing out">
    <parameter name="features" value="features/InSprint_11.5/ParallelRun_DW_CA_CS_OrderEntry_PageValidation.feature"/>
    <parameter name="scenario" value="CSR sees proper error message on entering the Invalid Flyer code in the flyer text box for Teacher Order Module on tabing out"/>
    <parameter name="driver.capabilities" value="{&#039;version&#039;: &#039;48.0&#039;,&#039;platform&#039;:&#039;Windows 10&#039;,&#039;name&#039;:&#039;DWCA&#039;}"/>
    <parameter name="driver.name" value="Chrome"/>
    <classes>
      <class name="com.scholastic.torque.runner.Run"/>
    </classes>
  </test> <!-- CSR sees proper error message on entering the Invalid Flyer code in the flyer text box for Teacher Order Module on tabing out -->
  <test name="CSR sees proper error message when less than 6 characters are entered in Flyer code text box for Teacher Order Module on tab out">
    <parameter name="features" value="features/InSprint_11.5/ParallelRun_DW_CA_CS_OrderEntry_PageValidation.feature"/>
    <parameter name="scenario" value="CSR sees proper error message when less than 6 characters are entered in Flyer code text box for Teacher Order Module on tab out"/>
    <parameter name="driver.capabilities" value="{&#039;version&#039;: &#039;48.0&#039;,&#039;platform&#039;:&#039;Windows 10&#039;,&#039;name&#039;:&#039;DWCA&#039;}"/>
    <parameter name="driver.name" value="Chrome"/>
    <classes>
      <class name="com.scholastic.torque.runner.Run"/>
    </classes>
  </test> <!-- CSR sees proper error message when less than 6 characters are entered in Flyer code text box for Teacher Order Module on tab out -->
  <test name="CSR sees proper error message on entering the Flyer code and tabing out from Flyer code text box for Teacher Order Module. The flyer code entered is  not active for the current month">
    <parameter name="features" value="features/InSprint_11.5/ParallelRun_DW_CA_CS_OrderEntry_PageValidation.feature"/>
    <parameter name="scenario" value="CSR sees proper error message on entering the Flyer code and tabing out from Flyer code text box for Teacher Order Module. The flyer code entered is  not active for the current month"/>
    <parameter name="driver.capabilities" value="{&#039;version&#039;: &#039;48.0&#039;,&#039;platform&#039;:&#039;Windows 10&#039;,&#039;name&#039;:&#039;DWCA&#039;}"/>
    <parameter name="driver.name" value="Chrome"/>
    <classes>
      <class name="com.scholastic.torque.runner.Run"/>
    </classes>
  </test> <!-- CSR sees proper error message on entering the Flyer code and tabing out from Flyer code text box for Teacher Order Module. The flyer code entered is  not active for the current month -->
  <test name="CSR tries to enter the [Paid Qty] for Teacher Module, as 3 digit">
    <parameter name="features" value="features/InSprint_11.5/ParallelRun_DW_CA_CS_OrderEntry_PageValidation.feature"/>
    <parameter name="scenario" value="CSR tries to enter the [Paid Qty] for Teacher Module, as 3 digit"/>
    <parameter name="driver.capabilities" value="{&#039;version&#039;: &#039;48.0&#039;,&#039;platform&#039;:&#039;Windows 10&#039;,&#039;name&#039;:&#039;DWCA&#039;}"/>
    <parameter name="driver.name" value="Chrome"/>
    <classes>
      <class name="com.scholastic.torque.runner.Run"/>
    </classes>
  </test> <!-- CSR tries to enter the [Paid Qty] for Teacher Module, as 3 digit -->
  <test name="CSR seen an Error message when CSR enters Flyercode, Invalid ItemNo#,QTY is blank and click [Proceed Checkout]">
    <parameter name="features" value="features/InSprint_11.5/ParallelRun_DW_CA_CS_OrderEntry_PageValidation.feature"/>
    <parameter name="scenario" value="CSR seen an Error message when CSR enters Flyercode, Invalid ItemNo#,QTY is blank and click [Proceed Checkout]"/>
    <parameter name="driver.capabilities" value="{&#039;version&#039;: &#039;48.0&#039;,&#039;platform&#039;:&#039;Windows 10&#039;,&#039;name&#039;:&#039;DWCA&#039;}"/>
    <parameter name="driver.name" value="Chrome"/>
    <classes>
      <class name="com.scholastic.torque.runner.Run"/>
    </classes>
  </test> <!-- CSR seen an Error message when CSR enters Flyercode, Invalid ItemNo#,QTY is blank and click [Proceed Checkout] -->
  <test name="CSR sees the message [Is this the correct number of items] and clicks on [Yes]">
    <parameter name="features" value="features/InSprint_11.5/ParallelRun_DW_CA_CS_OrderEntry_PageValidation.feature"/>
    <parameter name="scenario" value="CSR sees the message [Is this the correct number of items] and clicks on [Yes]"/>
    <parameter name="driver.capabilities" value="{&#039;version&#039;: &#039;48.0&#039;,&#039;platform&#039;:&#039;Windows 10&#039;,&#039;name&#039;:&#039;DWCA&#039;}"/>
    <parameter name="driver.name" value="Chrome"/>
    <classes>
      <class name="com.scholastic.torque.runner.Run"/>
    </classes>
  </test> <!-- CSR sees the message [Is this the correct number of items] and clicks on [Yes] -->
  <test name="CSR sees proper error message pop-up on clicking [Proceed to Checkout] when on Teacher order, valid flyer code is entered , multiple rows of Item# is entered with invalid item No and Qty">
    <parameter name="features" value="features/InSprint_11.5/ParallelRun_DW_CA_CS_OrderEntry_PageValidation.feature"/>
    <parameter name="scenario" value="CSR sees proper error message pop-up on clicking [Proceed to Checkout] when on Teacher order, valid flyer code is entered , multiple rows of Item# is entered with invalid item No and Qty"/>
    <parameter name="driver.capabilities" value="{&#039;version&#039;: &#039;48.0&#039;,&#039;platform&#039;:&#039;Windows 10&#039;,&#039;name&#039;:&#039;DWCA&#039;}"/>
    <parameter name="driver.name" value="Chrome"/>
    <classes>
      <class name="com.scholastic.torque.runner.Run"/>
    </classes>
  </test> <!-- CSR sees proper error message pop-up on clicking [Proceed to Checkout] when on Teacher order, valid flyer code is entered , multiple rows of Item# is entered with invalid item No and Qty -->
  <test name="CSR sees the message [Is this the correct number of items] and clicks on [No]">
    <parameter name="features" value="features/InSprint_11.5/ParallelRun_DW_CA_CS_OrderEntry_PageValidation.feature"/>
    <parameter name="scenario" value="CSR sees the message [Is this the correct number of items] and clicks on [No]"/>
    <parameter name="driver.capabilities" value="{&#039;version&#039;: &#039;48.0&#039;,&#039;platform&#039;:&#039;Windows 10&#039;,&#039;name&#039;:&#039;DWCA&#039;}"/>
    <parameter name="driver.name" value="Chrome"/>
    <classes>
      <class name="com.scholastic.torque.runner.Run"/>
    </classes>
  </test> <!-- CSR sees the message [Is this the correct number of items] and clicks on [No] -->
  <test name="CSR sees proper error message pop-up on clicking [Proceed to Checkout] when on Teacher order, valid flyer code is  entered , multiple rows of Item# is entered with invalid item No and Qty. And also rows with valid Item# and qty is present">
    <parameter name="features" value="features/InSprint_11.5/ParallelRun_DW_CA_CS_OrderEntry_PageValidation.feature"/>
    <parameter name="scenario" value="CSR sees proper error message pop-up on clicking [Proceed to Checkout] when on Teacher order, valid flyer code is  entered , multiple rows of Item# is entered with invalid item No and Qty. And also rows with valid Item# and qty is present"/>
    <parameter name="driver.capabilities" value="{&#039;version&#039;: &#039;48.0&#039;,&#039;platform&#039;:&#039;Windows 10&#039;,&#039;name&#039;:&#039;DWCA&#039;}"/>
    <parameter name="driver.name" value="Chrome"/>
    <classes>
      <class name="com.scholastic.torque.runner.Run"/>
    </classes>
  </test> <!-- CSR sees proper error message pop-up on clicking [Proceed to Checkout] when on Teacher order, valid flyer code is  entered , multiple rows of Item# is entered with invalid item No and Qty. And also rows with valid Item# and qty is present -->
  <test name="CSR sees the message [Is this the correct number of items] and the message automatically disappears">
    <parameter name="features" value="features/InSprint_11.5/ParallelRun_DW_CA_CS_OrderEntry_PageValidation.feature"/>
    <parameter name="scenario" value="CSR sees the message [Is this the correct number of items] and the message automatically disappears"/>
    <parameter name="driver.capabilities" value="{&#039;version&#039;: &#039;48.0&#039;,&#039;platform&#039;:&#039;Windows 10&#039;,&#039;name&#039;:&#039;DWCA&#039;}"/>
    <parameter name="driver.name" value="Chrome"/>
    <classes>
      <class name="com.scholastic.torque.runner.Run"/>
    </classes>
  </test> <!-- CSR sees the message [Is this the correct number of items] and the message automatically disappears -->
  <test name="CSR sees proper error message pop-up on clicking [Proceed to Checkout] when on Teacher order, flyer code is not entered , multiple rows of Item# is entered with invalid item No and Qty. And also rows with valid Item# and qty is present">
    <parameter name="features" value="features/InSprint_11.5/ParallelRun_DW_CA_CS_OrderEntry_PageValidation.feature"/>
    <parameter name="scenario" value="CSR sees proper error message pop-up on clicking [Proceed to Checkout] when on Teacher order, flyer code is not entered , multiple rows of Item# is entered with invalid item No and Qty. And also rows with valid Item# and qty is present"/>
    <parameter name="driver.capabilities" value="{&#039;version&#039;: &#039;48.0&#039;,&#039;platform&#039;:&#039;Windows 10&#039;,&#039;name&#039;:&#039;DWCA&#039;}"/>
    <parameter name="driver.name" value="Chrome"/>
    <classes>
      <class name="com.scholastic.torque.runner.Run"/>
    </classes>
  </test> <!-- CSR sees proper error message pop-up on clicking [Proceed to Checkout] when on Teacher order, flyer code is not entered , multiple rows of Item# is entered with invalid item No and Qty. And also rows with valid Item# and qty is present -->
  <test name="CSR sees the message [Flyer is Invalid ] and the message automatically disappears">
    <parameter name="features" value="features/InSprint_11.5/ParallelRun_DW_CA_CS_OrderEntry_PageValidation.feature"/>
    <parameter name="scenario" value="CSR sees the message [Flyer is Invalid ] and the message automatically disappears"/>
    <parameter name="driver.capabilities" value="{&#039;version&#039;: &#039;48.0&#039;,&#039;platform&#039;:&#039;Windows 10&#039;,&#039;name&#039;:&#039;DWCA&#039;}"/>
    <parameter name="driver.name" value="Chrome"/>
    <classes>
      <class name="com.scholastic.torque.runner.Run"/>
    </classes>
  </test> <!-- CSR sees the message [Flyer is Invalid ] and the message automatically disappears -->
  <test name="CSR sees proper error message pop-up on clicking [Proceed to Checkout] when on Teacher order following is present – Row of valid item#,row with Invalid Item#,row with blank Item#">
    <parameter name="features" value="features/InSprint_11.5/ParallelRun_DW_CA_CS_OrderEntry_PageValidation.feature"/>
    <parameter name="scenario" value="CSR sees proper error message pop-up on clicking [Proceed to Checkout] when on Teacher order following is present – Row of valid item#,row with Invalid Item#,row with blank Item#"/>
    <parameter name="driver.capabilities" value="{&#039;version&#039;: &#039;48.0&#039;,&#039;platform&#039;:&#039;Windows 10&#039;,&#039;name&#039;:&#039;DWCA&#039;}"/>
    <parameter name="driver.name" value="Chrome"/>
    <classes>
      <class name="com.scholastic.torque.runner.Run"/>
    </classes>
  </test> <!-- CSR sees proper error message pop-up on clicking [Proceed to Checkout] when on Teacher order following is present – Row of valid item#,row with Invalid Item#,row with blank Item# -->
  <test name="CSR sees the message [You must enter an item Number] and the message automatically disappears">
    <parameter name="features" value="features/InSprint_11.5/ParallelRun_DW_CA_CS_OrderEntry_PageValidation.feature"/>
    <parameter name="scenario" value="CSR sees the message [You must enter an item Number] and the message automatically disappears"/>
    <parameter name="driver.capabilities" value="{&#039;version&#039;: &#039;48.0&#039;,&#039;platform&#039;:&#039;Windows 10&#039;,&#039;name&#039;:&#039;DWCA&#039;}"/>
    <parameter name="driver.name" value="Chrome"/>
    <classes>
      <class name="com.scholastic.torque.runner.Run"/>
    </classes>
  </test> <!-- CSR sees the message [You must enter an item Number] and the message automatically disappears -->
  <test name="CSR sees the message [You must  enter a Quantity ] and the message automatically disappears">
    <parameter name="features" value="features/InSprint_11.5/ParallelRun_DW_CA_CS_OrderEntry_PageValidation.feature"/>
    <parameter name="scenario" value="CSR sees the message [You must  enter a Quantity ] and the message automatically disappears"/>
    <parameter name="driver.capabilities" value="{&#039;version&#039;: &#039;48.0&#039;,&#039;platform&#039;:&#039;Windows 10&#039;,&#039;name&#039;:&#039;DWCA&#039;}"/>
    <parameter name="driver.name" value="Chrome"/>
    <classes>
      <class name="com.scholastic.torque.runner.Run"/>
    </classes>
  </test> <!-- CSR sees the message [You must  enter a Quantity ] and the message automatically disappears -->
  <test name="CSR sees [Invalid Items] popup and click on [Continue] Button">
    <parameter name="features" value="features/InSprint_11.5/ParallelRun_DW_CA_CS_OrderEntry_PageValidation.feature"/>
    <parameter name="scenario" value="CSR sees [Invalid Items] popup and click on [Continue] Button"/>
    <parameter name="driver.capabilities" value="{&#039;version&#039;: &#039;48.0&#039;,&#039;platform&#039;:&#039;Windows 10&#039;,&#039;name&#039;:&#039;DWCA&#039;}"/>
    <parameter name="driver.name" value="Chrome"/>
    <classes>
      <class name="com.scholastic.torque.runner.Run"/>
    </classes>
  </test> <!-- CSR sees [Invalid Items] popup and click on [Continue] Button -->
  <test name="CSR sees [Invalid Items] popup and click on [Cancel] Button">
    <parameter name="features" value="features/InSprint_11.5/ParallelRun_DW_CA_CS_OrderEntry_PageValidation.feature"/>
    <parameter name="scenario" value="CSR sees [Invalid Items] popup and click on [Cancel] Button"/>
    <parameter name="driver.capabilities" value="{&#039;version&#039;: &#039;48.0&#039;,&#039;platform&#039;:&#039;Windows 10&#039;,&#039;name&#039;:&#039;DWCA&#039;}"/>
    <parameter name="driver.name" value="Chrome"/>
    <classes>
      <class name="com.scholastic.torque.runner.Run"/>
    </classes>
  </test> <!-- CSR sees [Invalid Items] popup and click on [Cancel] Button -->
  
  <test name="Review Cart tab highlights when CSR enters into the Review Cart page">
    <parameter name="features" value="features/InSprint_11.5/DW_CA_CS_ReviewCart_StepHeader.feature"/>
    <parameter name="scenario" value="Review Cart tab highlights when CSR enters into the Review Cart page"/>
    <parameter name="driver.capabilities" value="{&#039;version&#039;: &#039;48.0&#039;,&#039;platform&#039;:&#039;Windows 10&#039;,&#039;name&#039;:&#039;DWCA&#039;}"/>
    <parameter name="driver.name" value="Chrome"/>
    <classes>
      <class name="com.scholastic.torque.runner.Run"/>
    </classes>
  </test> <!-- Review Cart tab highlights when CSR enters into the Review Cart page -->
  <test name="Number of the Review Cart page displays in a bubble containing step header">
    <parameter name="features" value="features/InSprint_11.5/DW_CA_CS_ReviewCart_StepHeader.feature"/>
    <parameter name="scenario" value="Number of the Review Cart page displays in a bubble containing step header"/>
    <parameter name="driver.capabilities" value="{&#039;version&#039;: &#039;48.0&#039;,&#039;platform&#039;:&#039;Windows 10&#039;,&#039;name&#039;:&#039;DWCA&#039;}"/>
    <parameter name="driver.name" value="Chrome"/>
    <classes>
      <class name="com.scholastic.torque.runner.Run"/>
    </classes>
  </test> <!-- Number of the Review Cart page displays in a bubble containing step header -->
  
  <test name="As a CSR, I am presented with expanded Teacher catalogue table when landed on Review cart page">
    <parameter name="features" value="features/InSprint_11.5/ParallelRun_DW_CA_CS_YTO_TeacherCataloguesModule.feature"/>
    <parameter name="scenario" value="As a CSR, I am presented with expanded Teacher catalogue table when landed on Review cart page"/>
    <parameter name="driver.capabilities" value="{&#039;version&#039;: &#039;48.0&#039;,&#039;platform&#039;:&#039;Windows 10&#039;,&#039;name&#039;:&#039;DWCA&#039;}"/>
    <parameter name="driver.name" value="Chrome"/>
    <classes>
      <class name="com.scholastic.torque.runner.Run"/>
    </classes>
  </test> <!-- As a CSR, I am presented with expanded Teacher catalogue table when landed on Review cart page -->
  <test name="Teacher Catalogues table is not displayed when there are no teacher catalogue items added to cart">
    <parameter name="features" value="features/InSprint_11.5/ParallelRun_DW_CA_CS_YTO_TeacherCataloguesModule.feature"/>
    <parameter name="scenario" value="Teacher Catalogues table is not displayed when there are no teacher catalogue items added to cart"/>
    <parameter name="driver.capabilities" value="{&#039;version&#039;: &#039;48.0&#039;,&#039;platform&#039;:&#039;Windows 10&#039;,&#039;name&#039;:&#039;DWCA&#039;}"/>
    <parameter name="driver.name" value="Chrome"/>
    <classes>
      <class name="com.scholastic.torque.runner.Run"/>
    </classes>
  </test> <!-- Teacher Catalogues table is not displayed when there are no teacher catalogue items added to cart -->
  <test name="CSR can click contract - to hide the Teacher catalogues table">
    <parameter name="features" value="features/InSprint_11.5/ParallelRun_DW_CA_CS_YTO_TeacherCataloguesModule.feature"/>
    <parameter name="scenario" value="CSR can click contract - to hide the Teacher catalogues table"/>
    <parameter name="driver.capabilities" value="{&#039;version&#039;: &#039;48.0&#039;,&#039;platform&#039;:&#039;Windows 10&#039;,&#039;name&#039;:&#039;DWCA&#039;}"/>
    <parameter name="driver.name" value="Chrome"/>
    <classes>
      <class name="com.scholastic.torque.runner.Run"/>
    </classes>
  </test> <!-- CSR can click contract - to hide the Teacher catalogues table -->
  <test name="CSR can click expand + to show the Teacher catalogue table">
    <parameter name="features" value="features/InSprint_11.5/ParallelRun_DW_CA_CS_YTO_TeacherCataloguesModule.feature"/>
    <parameter name="scenario" value="CSR can click expand + to show the Teacher catalogue table"/>
    <parameter name="driver.capabilities" value="{&#039;version&#039;: &#039;48.0&#039;,&#039;platform&#039;:&#039;Windows 10&#039;,&#039;name&#039;:&#039;DWCA&#039;}"/>
    <parameter name="driver.name" value="Chrome"/>
    <classes>
      <class name="com.scholastic.torque.runner.Run"/>
    </classes>
  </test> <!-- CSR can click expand + to show the Teacher catalogue table -->
  <test name="Table structure when CSR adds items from Single flyer from Teacher Catalogue">
    <parameter name="features" value="features/InSprint_11.5/ParallelRun_DW_CA_CS_YTO_TeacherCataloguesModule.feature"/>
    <parameter name="scenario" value="Table structure when CSR adds items from Single flyer from Teacher Catalogue"/>
    <parameter name="driver.capabilities" value="{&#039;version&#039;: &#039;48.0&#039;,&#039;platform&#039;:&#039;Windows 10&#039;,&#039;name&#039;:&#039;DWCA&#039;}"/>
    <parameter name="driver.name" value="Chrome"/>
    <classes>
      <class name="com.scholastic.torque.runner.Run"/>
    </classes>
  </test> <!-- Table structure when CSR adds items from Single flyer from Teacher Catalogue -->
  <test name="Table structure and the item details when CSR adds items from Single flyer from Teacher Catalogue">
    <parameter name="features" value="features/InSprint_11.5/ParallelRun_DW_CA_CS_YTO_TeacherCataloguesModule.feature"/>
    <parameter name="scenario" value="Table structure and the item details when CSR adds items from Single flyer from Teacher Catalogue"/>
    <parameter name="driver.capabilities" value="{&#039;version&#039;: &#039;48.0&#039;,&#039;platform&#039;:&#039;Windows 10&#039;,&#039;name&#039;:&#039;DWCA&#039;}"/>
    <parameter name="driver.name" value="Chrome"/>
    <classes>
      <class name="com.scholastic.torque.runner.Run"/>
    </classes>
  </test> <!-- Table structure and the item details when CSR adds items from Single flyer from Teacher Catalogue -->
  <test name="Table Structure when CSR adds items from Multiple flyers different months">
    <parameter name="features" value="features/InSprint_11.5/ParallelRun_DW_CA_CS_YTO_TeacherCataloguesModule.feature"/>
    <parameter name="scenario" value="Table Structure when CSR adds items from Multiple flyers different months"/>
    <parameter name="driver.capabilities" value="{&#039;version&#039;: &#039;48.0&#039;,&#039;platform&#039;:&#039;Windows 10&#039;,&#039;name&#039;:&#039;DWCA&#039;}"/>
    <parameter name="driver.name" value="Chrome"/>
    <classes>
      <class name="com.scholastic.torque.runner.Run"/>
    </classes>
  </test> <!-- Table Structure when CSR adds items from Multiple flyers different months -->
  <test name="Correct subtotals, totals, taxes display for Teacher Catalogues when multiple items are added from Single flyer for province with applicable taxes as GST &amp; QST">
    <parameter name="features" value="features/InSprint_11.5/ParallelRun_DW_CA_CS_YTO_TeacherCataloguesModule.feature"/>
    <parameter name="scenario" value="Correct subtotals, totals, taxes display for Teacher Catalogues when multiple items are added from Single flyer for province with applicable taxes as GST &amp; QST"/>
    <parameter name="driver.capabilities" value="{&#039;version&#039;: &#039;48.0&#039;,&#039;platform&#039;:&#039;Windows 10&#039;,&#039;name&#039;:&#039;DWCA&#039;}"/>
    <parameter name="driver.name" value="Chrome"/>
    <classes>
      <class name="com.scholastic.torque.runner.Run"/>
    </classes>
  </test> <!-- Correct subtotals, totals, taxes display for Teacher Catalogues when multiple items are added from Single flyer for province with applicable taxes as GST & QST -->
  <test name="Correct subtotals, totals, taxes display for Teacher Catalogues when multiple items are added from Single flyer for province with applicable taxes as GST &amp; QST1">
    <parameter name="features" value="features/InSprint_11.5/ParallelRun_DW_CA_CS_YTO_TeacherCataloguesModule.feature"/>
    <parameter name="scenario" value="Correct subtotals, totals, taxes display for Teacher Catalogues when multiple items are added from Single flyer for province with applicable taxes as GST &amp; QST1"/>
    <parameter name="driver.capabilities" value="{&#039;version&#039;: &#039;48.0&#039;,&#039;platform&#039;:&#039;Windows 10&#039;,&#039;name&#039;:&#039;DWCA&#039;}"/>
    <parameter name="driver.name" value="Chrome"/>
    <classes>
      <class name="com.scholastic.torque.runner.Run"/>
    </classes>
  </test> <!-- Correct subtotals, totals, taxes display for Teacher Catalogues when multiple items are added from Single flyer for province with applicable taxes as GST & QST1 -->
  <test name="Correct subtotals, totals, taxes display for Teacher Catalogues when multiple items are added from multiple flyer for province with applicable taxes as GST &amp; PST">
    <parameter name="features" value="features/InSprint_11.5/ParallelRun_DW_CA_CS_YTO_TeacherCataloguesModule.feature"/>
    <parameter name="scenario" value="Correct subtotals, totals, taxes display for Teacher Catalogues when multiple items are added from multiple flyer for province with applicable taxes as GST &amp; PST"/>
    <parameter name="driver.capabilities" value="{&#039;version&#039;: &#039;48.0&#039;,&#039;platform&#039;:&#039;Windows 10&#039;,&#039;name&#039;:&#039;DWCA&#039;}"/>
    <parameter name="driver.name" value="Chrome"/>
    <classes>
      <class name="com.scholastic.torque.runner.Run"/>
    </classes>
  </test> <!-- Correct subtotals, totals, taxes display for Teacher Catalogues when multiple items are added from multiple flyer for province with applicable taxes as GST & PST -->
  <test name="Correct subtotals, totals, taxes display for Teacher Catalogues when multiple items are added from multiple flyer for province with applicable taxes as HST_NL">
    <parameter name="features" value="features/InSprint_11.5/ParallelRun_DW_CA_CS_YTO_TeacherCataloguesModule.feature"/>
    <parameter name="scenario" value="Correct subtotals, totals, taxes display for Teacher Catalogues when multiple items are added from multiple flyer for province with applicable taxes as HST_NL"/>
    <parameter name="driver.capabilities" value="{&#039;version&#039;: &#039;48.0&#039;,&#039;platform&#039;:&#039;Windows 10&#039;,&#039;name&#039;:&#039;DWCA&#039;}"/>
    <parameter name="driver.name" value="Chrome"/>
    <classes>
      <class name="com.scholastic.torque.runner.Run"/>
    </classes>
  </test> <!-- Correct subtotals, totals, taxes display for Teacher Catalogues when multiple items are added from multiple flyer for province with applicable taxes as HST_NL -->
  <test name="Correct subtotals, totals, taxes display for Teacher Catalogues when multiple items are added from multiple flyer for province with applicable taxes as HST_NB">
    <parameter name="features" value="features/InSprint_11.5/ParallelRun_DW_CA_CS_YTO_TeacherCataloguesModule.feature"/>
    <parameter name="scenario" value="Correct subtotals, totals, taxes display for Teacher Catalogues when multiple items are added from multiple flyer for province with applicable taxes as HST_NB"/>
    <parameter name="driver.capabilities" value="{&#039;version&#039;: &#039;48.0&#039;,&#039;platform&#039;:&#039;Windows 10&#039;,&#039;name&#039;:&#039;DWCA&#039;}"/>
    <parameter name="driver.name" value="Chrome"/>
    <classes>
      <class name="com.scholastic.torque.runner.Run"/>
    </classes>
  </test> <!-- Correct subtotals, totals, taxes display for Teacher Catalogues when multiple items are added from multiple flyer for province with applicable taxes as HST_NB -->
  <test name="Correct subtotals, totals, taxes display for Teacher Catalogues when multiple items are added from multiple flyer for province with applicable taxes as HST_NS">
    <parameter name="features" value="features/InSprint_11.5/ParallelRun_DW_CA_CS_YTO_TeacherCataloguesModule.feature"/>
    <parameter name="scenario" value="Correct subtotals, totals, taxes display for Teacher Catalogues when multiple items are added from multiple flyer for province with applicable taxes as HST_NS"/>
    <parameter name="driver.capabilities" value="{&#039;version&#039;: &#039;48.0&#039;,&#039;platform&#039;:&#039;Windows 10&#039;,&#039;name&#039;:&#039;DWCA&#039;}"/>
    <parameter name="driver.name" value="Chrome"/>
    <classes>
      <class name="com.scholastic.torque.runner.Run"/>
    </classes>
  </test> <!-- Correct subtotals, totals, taxes display for Teacher Catalogues when multiple items are added from multiple flyer for province with applicable taxes as HST_NS -->
  <test name="Correct subtotals, totals, taxes display for Teacher Catalogues when multiple items are added from multiple flyer for province with applicable taxes as HST_ON">
    <parameter name="features" value="features/InSprint_11.5/ParallelRun_DW_CA_CS_YTO_TeacherCataloguesModule.feature"/>
    <parameter name="scenario" value="Correct subtotals, totals, taxes display for Teacher Catalogues when multiple items are added from multiple flyer for province with applicable taxes as HST_ON"/>
    <parameter name="driver.capabilities" value="{&#039;version&#039;: &#039;48.0&#039;,&#039;platform&#039;:&#039;Windows 10&#039;,&#039;name&#039;:&#039;DWCA&#039;}"/>
    <parameter name="driver.name" value="Chrome"/>
    <classes>
      <class name="com.scholastic.torque.runner.Run"/>
    </classes>
  </test> <!-- Correct subtotals, totals, taxes display for Teacher Catalogues when multiple items are added from multiple flyer for province with applicable taxes as HST_ON -->
  <test name="Correct subtotals, totals, taxes display for Teacher Catalogues when multiple items are added from multiple flyer for province with applicable taxes as HST_PE">
    <parameter name="features" value="features/InSprint_11.5/ParallelRun_DW_CA_CS_YTO_TeacherCataloguesModule.feature"/>
    <parameter name="scenario" value="Correct subtotals, totals, taxes display for Teacher Catalogues when multiple items are added from multiple flyer for province with applicable taxes as HST_PE"/>
    <parameter name="driver.capabilities" value="{&#039;version&#039;: &#039;48.0&#039;,&#039;platform&#039;:&#039;Windows 10&#039;,&#039;name&#039;:&#039;DWCA&#039;}"/>
    <parameter name="driver.name" value="Chrome"/>
    <classes>
      <class name="com.scholastic.torque.runner.Run"/>
    </classes>
  </test> <!-- Correct subtotals, totals, taxes display for Teacher Catalogues when multiple items are added from multiple flyer for province with applicable taxes as HST_PE -->
  <test name="Correct subtotals, totals, taxes display for Teacher Catalogues when multiple items are added from multiple flyer for province with applicable taxes as GST_AB">
    <parameter name="features" value="features/InSprint_11.5/ParallelRun_DW_CA_CS_YTO_TeacherCataloguesModule.feature"/>
    <parameter name="scenario" value="Correct subtotals, totals, taxes display for Teacher Catalogues when multiple items are added from multiple flyer for province with applicable taxes as GST_AB"/>
    <parameter name="driver.capabilities" value="{&#039;version&#039;: &#039;48.0&#039;,&#039;platform&#039;:&#039;Windows 10&#039;,&#039;name&#039;:&#039;DWCA&#039;}"/>
    <parameter name="driver.name" value="Chrome"/>
    <classes>
      <class name="com.scholastic.torque.runner.Run"/>
    </classes>
  </test> <!-- Correct subtotals, totals, taxes display for Teacher Catalogues when multiple items are added from multiple flyer for province with applicable taxes as GST_AB -->
  <test name="Correct subtotals, totals, taxes display for Teacher Catalogues when multiple items are added from multiple flyer for province with applicable taxes as GST_MB">
    <parameter name="features" value="features/InSprint_11.5/ParallelRun_DW_CA_CS_YTO_TeacherCataloguesModule.feature"/>
    <parameter name="scenario" value="Correct subtotals, totals, taxes display for Teacher Catalogues when multiple items are added from multiple flyer for province with applicable taxes as GST_MB"/>
    <parameter name="driver.capabilities" value="{&#039;version&#039;: &#039;48.0&#039;,&#039;platform&#039;:&#039;Windows 10&#039;,&#039;name&#039;:&#039;DWCA&#039;}"/>
    <parameter name="driver.name" value="Chrome"/>
    <classes>
      <class name="com.scholastic.torque.runner.Run"/>
    </classes>
  </test> <!-- Correct subtotals, totals, taxes display for Teacher Catalogues when multiple items are added from multiple flyer for province with applicable taxes as GST_MB -->
  <test name="Correct subtotals, totals, taxes display for Teacher Catalogues when multiple items are added from multiple flyer for province with applicable taxes as GST_NT">
    <parameter name="features" value="features/InSprint_11.5/ParallelRun_DW_CA_CS_YTO_TeacherCataloguesModule.feature"/>
    <parameter name="scenario" value="Correct subtotals, totals, taxes display for Teacher Catalogues when multiple items are added from multiple flyer for province with applicable taxes as GST_NT"/>
    <parameter name="driver.capabilities" value="{&#039;version&#039;: &#039;48.0&#039;,&#039;platform&#039;:&#039;Windows 10&#039;,&#039;name&#039;:&#039;DWCA&#039;}"/>
    <parameter name="driver.name" value="Chrome"/>
    <classes>
      <class name="com.scholastic.torque.runner.Run"/>
    </classes>
  </test> <!-- Correct subtotals, totals, taxes display for Teacher Catalogues when multiple items are added from multiple flyer for province with applicable taxes as GST_NT -->
  <test name="Correct subtotals, totals, taxes display for Teacher Catalogues when multiple items are added from multiple flyer for province with applicable taxes as GST_NU">
    <parameter name="features" value="features/InSprint_11.5/ParallelRun_DW_CA_CS_YTO_TeacherCataloguesModule.feature"/>
    <parameter name="scenario" value="Correct subtotals, totals, taxes display for Teacher Catalogues when multiple items are added from multiple flyer for province with applicable taxes as GST_NU"/>
    <parameter name="driver.capabilities" value="{&#039;version&#039;: &#039;48.0&#039;,&#039;platform&#039;:&#039;Windows 10&#039;,&#039;name&#039;:&#039;DWCA&#039;}"/>
    <parameter name="driver.name" value="Chrome"/>
    <classes>
      <class name="com.scholastic.torque.runner.Run"/>
    </classes>
  </test> <!-- Correct subtotals, totals, taxes display for Teacher Catalogues when multiple items are added from multiple flyer for province with applicable taxes as GST_NU -->
  <test name="Correct subtotals, totals, taxes display for Teacher Catalogues when multiple items are added from multiple flyer for province with applicable taxes as GST_SK">
    <parameter name="features" value="features/InSprint_11.5/ParallelRun_DW_CA_CS_YTO_TeacherCataloguesModule.feature"/>
    <parameter name="scenario" value="Correct subtotals, totals, taxes display for Teacher Catalogues when multiple items are added from multiple flyer for province with applicable taxes as GST_SK"/>
    <parameter name="driver.capabilities" value="{&#039;version&#039;: &#039;48.0&#039;,&#039;platform&#039;:&#039;Windows 10&#039;,&#039;name&#039;:&#039;DWCA&#039;}"/>
    <parameter name="driver.name" value="Chrome"/>
    <classes>
      <class name="com.scholastic.torque.runner.Run"/>
    </classes>
  </test> <!-- Correct subtotals, totals, taxes display for Teacher Catalogues when multiple items are added from multiple flyer for province with applicable taxes as GST_SK -->
  <test name="Correct subtotals, totals, taxes display for Teacher Catalogues when multiple items are added from multiple flyer for province with applicable taxes as GST_YT">
    <parameter name="features" value="features/InSprint_11.5/ParallelRun_DW_CA_CS_YTO_TeacherCataloguesModule.feature"/>
    <parameter name="scenario" value="Correct subtotals, totals, taxes display for Teacher Catalogues when multiple items are added from multiple flyer for province with applicable taxes as GST_YT"/>
    <parameter name="driver.capabilities" value="{&#039;version&#039;: &#039;48.0&#039;,&#039;platform&#039;:&#039;Windows 10&#039;,&#039;name&#039;:&#039;DWCA&#039;}"/>
    <parameter name="driver.name" value="Chrome"/>
    <classes>
      <class name="com.scholastic.torque.runner.Run"/>
    </classes>
  </test> <!-- Correct subtotals, totals, taxes display for Teacher Catalogues when multiple items are added from multiple flyer for province with applicable taxes as GST_YT -->
  <test name="No taxes are charged for Teacher Catalogues for tax exempted schools for province with applicable taxes as GST &amp; PST">
    <parameter name="features" value="features/InSprint_11.5/ParallelRun_DW_CA_CS_YTO_TeacherCataloguesModule.feature"/>
    <parameter name="scenario" value="No taxes are charged for Teacher Catalogues for tax exempted schools for province with applicable taxes as GST &amp; PST"/>
    <parameter name="driver.capabilities" value="{&#039;version&#039;: &#039;48.0&#039;,&#039;platform&#039;:&#039;Windows 10&#039;,&#039;name&#039;:&#039;DWCA&#039;}"/>
    <parameter name="driver.name" value="Chrome"/>
    <classes>
      <class name="com.scholastic.torque.runner.Run"/>
    </classes>
  </test> <!-- No taxes are charged for Teacher Catalogues for tax exempted schools for province with applicable taxes as GST & PST -->
</suite> <!-- Demandware -->